<Gesture Name = "Infinity">
		<Point X = "-4.230769" Y = "0.2675587"/>
		<Point X = "-4.206456" Y = "0.6582254"/>
		<Point X = "-3.911691" Y = "0.9217615"/>
		<Point X = "-3.55722" Y = "1.086956"/>
		<Point X = "-3.160974" Y = "1.028647"/>
		<Point X = "-2.857708" Y = "0.7748564"/>
		<Point X = "-2.56724" Y = "0.4990019"/>
		<Point X = "-2.20284" Y = "0.3217936"/>
		<Point X = "-1.841486" Y = "0.152523"/>
		<Point X = "-1.463272" Y = "0.004795564"/>
		<Point X = "-1.076526" Y = "-0.117057"/>
		<Point X = "-0.6747861" Y = "-0.1832103"/>
		<Point X = "-0.2671252" Y = "-0.2006689"/>
		<Point X = "0.1377147" Y = "-0.1756397"/>
		<Point X = "0.5189802" Y = "-0.0498744"/>
		<Point X = "0.8422207" Y = "0.184736"/>
		<Point X = "1.030631" Y = "0.5395231"/>
		<Point X = "0.8686113" Y = "0.869565"/>
		<Point X = "0.4957024" Y = "0.986622"/>
		<Point X = "0.092586" Y = "0.9796303"/>
		<Point X = "-0.2909136" Y = "0.8578876"/>
		<Point X = "-0.6611421" Y = "0.7003046"/>
		<Point X = "-1.031415" Y = "0.5331256"/>
		<Point X = "-1.391092" Y = "0.3488211"/>
		<Point X = "-1.759556" Y = "0.1788399"/>
		<Point X = "-2.134127" Y = "0.02929228"/>
		<Point X = "-2.521231" Y = "-0.09052853"/>
		<Point X = "-2.91965" Y = "-0.1658698"/>
		<Point X = "-3.324033" Y = "-0.1505017"/>
		<Point X = "-3.694737" Y = "0.007903636"/>
		<Point X = "-4.046409" Y = "0.1835328"/>
		<Point X = "-4.247489" Y = "0.518393"/>
</Gesture>
